nougat_router/__init__.py
nougat_router/exceptions.py
nougat_router/param.py
nougat_router/route.py
nougat_router/router.py
nougat_router/routing.py
nougat_router/utils.py
nougat_router-0.0.2.dist-info/METADATA
nougat_router-0.0.2.dist-info/RECORD
nougat_router-0.0.2.dist-info/WHEEL
nougat_router-0.0.2.dist-info/top_level.txt
