Metadata-Version: 2.1
Name: nougat-router
Version: 0.0.2
Summary: Router for nougat web framework supported restful api and parameters' validation
Home-page: https://github.com/Kilerd/nougat_router
Author: Kilerd Chan
License: MIT
Keywords: web async router restful param
Platform: UNKNOWN
Classifier: Development Status :: 3 - Alpha
Classifier: Intended Audience :: Developers
Classifier: Environment :: Web Environment
Classifier: License :: OSI Approved :: MIT License
Classifier: Programming Language :: Python :: 3.6
Requires-Python: >=3.6
Requires-Dist: nougat
